README.txt
setup.py
PyBencoder/__init__.py
PyBencoder/bencoder.py
PyBencoder/benexceptions.py
pybencoder.egg-info/PKG-INFO
pybencoder.egg-info/SOURCES.txt
pybencoder.egg-info/dependency_links.txt
pybencoder.egg-info/top_level.txt