Metadata-Version: 1.0
Name: pybencoder
Version: 1.0
Summary: Module to work with bencoded strings.
Home-page: https://github.com/cristianav/PyBencoder
Author: Cristian Năvălici
Author-email: ncristian@lemonsoftware.eu
License: LGPL
Download-URL: https://github.com/cristianav/PyBencoder/zipball/master
Keywords: bencoding,encode,decode,bittorrent
Platform: POSIX
Platform: Windows
Classifier: Development Status :: 3 - Alpha
Classifier: Environment :: Other Environment
Classifier: Intended Audience :: Developers
Classifier: License :: OSI Approved :: GNU Library or Lesser General Public License (LGPL)
Classifier: Operating System :: OS Independent
Classifier: Programming Language :: Python :: 2
Classifier: Programming Language :: Python :: 3
Classifier: Topic :: Software Development :: Libraries :: Python Modules
